[
  {
    "id": 1,
    "img": "https://i.ibb.co/7NmjhHB/food-1.jpg",
    "title": "Better Food Access",
    "category": "food",
    "text_button_bg": "#F87147",
    "category_bg": "#FDD2C4",
    "card_bg": "#FEEAE3",
    "description": "Make a difference by donating food to our Food donation collection.",
    "price": 300
  },
  {
    "id": 2,
    "img": "https://i.ibb.co/6s3d6dM/water-1.jpg",
    "title": "Clean Water for Children",
    "category": "food",
    "text_button_bg": "#F87147",
    "category_bg": "#FDD2C4",
    "card_bg": "#FEEAE3",
    "description": "Support health initiatives and provide essential care with our Health donation collection.",
    "price": 500
  },
  {
    "id": 3,
    "img": "https://i.ibb.co/1RG1krd/education-1.jpg",
    "title": "Empower Education",
    "category": "education",
    "text_button_bg": "#FF444A",
    "category_bg": "#FFC3C5",
    "card_bg": "#FFE3E4",
    "description": "Empower students and educators through our Education donation collection.",
    "price": 900
  },
  {
    "id": 4,
    "img": "https://i.ibb.co/hmmZpq0/food-2.jpg",
    "title": "Fight Hunger",
    "category": "food",
    "text_button_bg": "#F87147",
    "category_bg": "#FDD2C4",
    "card_bg": "#FEEAE3",
    "description": "Help those in need by contributing to our Food donation collection.",
    "price": 200
  },
  {
    "id": 5,
    "img": "https://i.ibb.co/QMb2DCZ/health-2.jpg",
    "title": "Health & Wellness",
    "category": "health",
    "text_button_bg": "#0052FF",
    "category_bg": "#AEC8FF",
    "card_bg": "#D9E5FF",
    "description": "Support health causes and provide hope through our Health donation collection.",
    "price": 400
  },
  {
    "id": 6,
    "img": "https://i.ibb.co/Q8JR3VC/clothes-2.jpg",
    "title": "Clothing Drive",
    "category": "clothing",
    "text_button_bg": "#79C23F",
    "category_bg": "#D4ECC1",
    "card_bg": "#EBF6E2",
    "description": "Give the gift of warmth and dignity with our Clothing donation collection.",
    "price": 700
  },
  {
    "id": 7,
    "img": "https://i.ibb.co/L5zhk8P/education-2.jpg",
    "title": "Invest in Education",
    "category": "education",
    "text_button_bg": "#FF444A",
    "category_bg": "#FFC3C5",
    "card_bg": "#FFE3E4",
    "description": "Invest in the future by supporting education through our Education donation collection.",
    "price": 300
  },
  {
    "id": 8,
    "img": "https://i.ibb.co/T4zsLzh/water-4.jpg",
    "title": "Fight Hunger - Support",
    "category": "food",
    "text_button_bg": "#F87147",
    "category_bg": "#FDD2C4",
    "card_bg": "#FEEAE3",
    "description": "Make a difference in someone's life with a donation to our Food collection.",
    "price": 2000
  },
  {
    "id": 9,
    "img": "https://i.ibb.co/dK24PFy/health-1.jpg",
    "title": "Support Health Initiatives",
    "category": "health",
    "text_button_bg": "#0052FF",
    "category_bg": "#AEC8FF",
    "card_bg": "#D9E5FF",
    "description": "Support health causes and provide hope through our Health donation collection.",
    "price": 100
  },
  {
    "id": 10,
    "img": "https://i.ibb.co/nsrh6PP/clothes-1.jpg",
    "title": "Warmth & Dignity",
    "category": "clothing",
    "text_button_bg": "#79C23F",
    "category_bg": "#D4ECC1",
    "card_bg": "#EBF6E2",
    "description": "Give the gift of warmth and dignity with our Clothing donation collection.",
    "price": 1500
  },
  {
    "id": 11,
    "img": "https://i.ibb.co/ZxdZtnR/education-3.jpg",
    "title": "Education Support",
    "category": "education",
    "text_button_bg": "#FF444A",
    "category_bg": "#FFC3C5",
    "card_bg": "#FFE3E4",
    "description": "Invest in the future by supporting education through our Education donation collection.",
    "price": 800
  },
  {
    "id": 12,
    "img": "https://i.ibb.co/Q62yqzN/water-3.jpg",
    "title": "Make a Difference - Donate",
    "category": "food",
    "text_button_bg": "#F87147",
    "category_bg": "#FDD2C4",
    "card_bg": "#FEEAE3",
    "description": "Make a difference in someone's life with a donation to our Food collection.",
    "price": 600
  }
]
